.gitignore
CHANGES.txt
MANIFEST.in
README.rst
bootstrap.py
buildout.cfg
collective.metarobots-configure.zcml
setup.py
collective/__init__.py
collective.metarobots.egg-info/PKG-INFO
collective.metarobots.egg-info/SOURCES.txt
collective.metarobots.egg-info/dependency_links.txt
collective.metarobots.egg-info/entry_points.txt
collective.metarobots.egg-info/namespace_packages.txt
collective.metarobots.egg-info/not-zip-safe
collective.metarobots.egg-info/requires.txt
collective.metarobots.egg-info/top_level.txt
collective/metarobots/__init__.py
collective/metarobots/configure.zcml
collective/metarobots/layer.py
collective/metarobots/rebuild_i18n.sh
collective/metarobots/tag.pt
collective/metarobots/tag.py
collective/metarobots/testing.py
collective/metarobots/upgrades.py
collective/metarobots/upgrades.zcml
collective/metarobots/locales/collective.metarobots.pot
collective/metarobots/locales/en/LC_MESSAGES/collective.metarobots.po
collective/metarobots/locales/fr/LC_MESSAGES/collective.metarobots.po
collective/metarobots/profiles/default/browserlayer.xml
collective/metarobots/profiles/default/controlpanel.xml
collective/metarobots/profiles/default/metadata.xml
collective/metarobots/profiles/default/registry.xml
collective/metarobots/tests/__init__.py
collective/metarobots/tests/base.py
collective/metarobots/tests/test_setup.py