Metadata-Version: 1.0
Name: collective.metarobots
Version: 1.1
Summary: Add meta tag robots to Plone
Home-page: https://github.com/collective/collective.metarobots
Author: JeanMichel FRANCOIS aka toutpt
Author-email: toutpt@gmail.com
License: GPL
Keywords: plone robots noindex nofollow
Platform: UNKNOWN
Classifier: Programming Language :: Python
Classifier: Framework :: Plone
Classifier: Framework :: Plone :: 4.0
Classifier: Framework :: Plone :: 4.1
Classifier: Framework :: Plone :: 4.2
